string_locator/locator.py
string_locator/main.py
string_locator-1.1.0.dist-info/LICENSE
string_locator-1.1.0.dist-info/METADATA
string_locator-1.1.0.dist-info/WHEEL
string_locator-1.1.0.dist-info/entry_points.txt
string_locator-1.1.0.dist-info/top_level.txt
string_locator-1.1.0.dist-info/RECORD
