Metadata-Version: 2.1
Name: string-locator
Version: 1.1.0
Summary: A python package to find the files that contain a given string inside a given path
Home-page: https://github.com/sriragjayakumar/string-locator.git
Author: Srirag Jayakumar
Author-email: sriragjayakumar@gmail.com
License: MIT
Platform: UNKNOWN
Classifier: License :: OSI Approved :: MIT License
Classifier: Programming Language :: Python :: 3.8
Classifier: Programming Language :: Python :: 3.7
